{
    "no_release": false,
    "timer": 20,
    "exclude_url": "^https://\n.*://(10|172|192).d+.d+.d+\nlocalhost\nnicovideo.jp\nyoutube.com\nxvideos.com\n.(pdf|jpg|png|gif)^",
    "regex_insensitive": true,
    "enable_auto_purge": false,
    "remaiming_memory": 500,
    "max_history": 1,
    "max_sessions": 10,
    "purging_all_tabs_except_active": false,
    "max_opening_tabs": 5,
    "interval_timing": 300,
    "new_tab_opens_with_purged_tab": false,
    "get_title_when_does_not_title": true,
    "not_purge_playsound_tab": true,
    "restored_type": "restore_to_original_window",
    "keybind_release": "{}",
    "keybind_switch_not_release": "{}",
    "keybind_all_purge": "{}",
    "keybind_all_purge_without_exclude_list": "{}",
    "keybind_all_unpurge": "{}",
    "keybind_exclude_url": "nicovideo.jp\nyoutube.com",
    "keybind_regex_insensitive": true
}
